SqApiTool/Exec.py
SqApiTool/__init__.py
SqApiTool/run.py
SqApiTool/test_template.py
SqApiTool/utils/__init__.py
SqApiTool/utils/apiAssert.py
SqApiTool/utils/handle_excel.py
SqApiTool/utils/handle_loguru.py
SqApiTool/utils/handle_md5.py
sq_api_tool-0.0.2.dist-info/LICENSE
sq_api_tool-0.0.2.dist-info/METADATA
sq_api_tool-0.0.2.dist-info/WHEEL
sq_api_tool-0.0.2.dist-info/top_level.txt
sq_api_tool-0.0.2.dist-info/RECORD
